[{"Model":"V63","Truc":"Songa","Roto":"Songa","Temperature":0.0,"Pos_Roto1":[0.0,0.0,0.0],"Pos_Roto2":[0.0,0.0,0.0],"Pos_Roto3":[0.0,0.0,0.0],"Pos_Roto4":[0.0,0.0,0.0],"Pos_Roto5":[0.0,0.0,0.0],"Pos_Roto6":[0.0,0.0,0.0],"Pos_Roto7":[0.0,0.0,0.0],"Pos_Truc1":[0.0,0.0,0.0],"Pos_Truc2":[0.0,0.0,0.0],"Pos_Truc3":[0.0,0.0,0.0],"Pos_Truc4":[0.0,0.0,0.0],"Pos_Truc5":[0.0,0.0,0.0],"Pos_Truc6":[0.0,0.0,0.0],"Pos_Tha_Cum_Ktr":[0.0,0.0,0.0],"Pos_Nang_Kep_Cum_Ktr":[0.0,0.0],"Pos_Gap_Cum_Lap":[0.0,0.0,0.0],"Pos_Lap_Cum_Lap":[0.0,0.0,0.0],"Pos_Nhan_Truc":[0.0,0.0,0.0],"Pos_Nang_Kep_Cum_Lap":[0.0,0.0],"Pos_Tha_Ban_Xoay":[0.0,0.0,0.0],"Offset_Tha_Roto":0.0,"Cong_Suat_Nung":0.0,"Time_Blow":0.0,"Temperature_LamMat":0.0,"Z_Safety":0.0,"Pos_LapTruc":0.0,"LoaiTruc":0.0}]